{
  "title": "GitHub Move Languages Daily Trending",
  "description": "Daily Trending of Move Languages in GitHub",
  "link": "https://github.com/isboyjc/github-trending-api",
  "pubDate": "Fri, 16 Aug 2024 19:02:20 GMT",
  "items": [
    {
      "title": "pontem-network/liquidswap",
      "url": "https://github.com/pontem-network/liquidswap",
      "description": "AMM core smart contracts",
      "language": "Move",
      "languageColor": "#4a137a",
      "stars": "165",
      "forks": "73",
      "addStars": "0",
      "contributors": [
        {
          "avatar": "https://avatars.githubusercontent.com/u/7782923?s=40&v=4",
          "name": "borispovod",
          "url": "https://github.com/borispovod"
        },
        {
          "avatar": "https://avatars.githubusercontent.com/u/2341827?s=40&v=4",
          "name": "mkurnikov",
          "url": "https://github.com/mkurnikov"
        },
        {
          "avatar": "https://avatars.githubusercontent.com/u/86858790?s=40&v=4",
          "name": "sunmoon11100",
          "url": "https://github.com/sunmoon11100"
        },
        {
          "avatar": "https://avatars.githubusercontent.com/u/32911557?s=40&v=4",
          "name": "vladimirovmm",
          "url": "https://github.com/vladimirovmm"
        },
        {
          "avatar": "https://avatars.githubusercontent.com/u/88060356?s=40&v=4",
          "name": "gaquarius",
          "url": "https://github.com/gaquarius"
        }
      ]
    }
  ]
}