{
  "title": "GitHub Scala Languages Daily Trending",
  "description": "Daily Trending of Scala Languages in GitHub",
  "link": "https://github.com/isboyjc/github-trending-api",
  "pubDate": "Sat, 14 Sep 2024 02:09:21 GMT",
  "items": [
    {
      "title": "OpenXiangShan/XiangShan",
      "url": "https://github.com/OpenXiangShan/XiangShan",
      "description": "Open-source high-performance RISC-V processor",
      "language": "Scala",
      "languageColor": "#c22d40",
      "stars": "4,705",
      "forks": "644",
      "addStars": "4",
      "contributors": [
        {
          "avatar": "https://avatars.githubusercontent.com/u/14199583?s=40&v=4",
          "name": "poemonsense",
          "url": "https://github.com/poemonsense"
        },
        {
          "avatar": "https://avatars.githubusercontent.com/u/28356235?s=40&v=4",
          "name": "AugustusWillisWang",
          "url": "https://github.com/AugustusWillisWang"
        },
        {
          "avatar": "https://avatars.githubusercontent.com/u/32027544?s=40&v=4",
          "name": "Lingrui98",
          "url": "https://github.com/Lingrui98"
        },
        {
          "avatar": "https://avatars.githubusercontent.com/u/45601194?s=40&v=4",
          "name": "ljwljwljwljw",
          "url": "https://github.com/ljwljwljwljw"
        },
        {
          "avatar": "https://avatars.githubusercontent.com/u/35767095?s=40&v=4",
          "name": "Lemover",
          "url": "https://github.com/Lemover"
        }
      ]
    },
    {
      "title": "lichess-org/lila",
      "url": "https://github.com/lichess-org/lila",
      "description": "♞ lichess.org: the forever free, adless and open source chess server ♞",
      "language": "Scala",
      "languageColor": "#c22d40",
      "stars": "15,051",
      "forks": "2,232",
      "addStars": "4",
      "contributors": [
        {
          "avatar": "https://avatars.githubusercontent.com/u/140370?s=40&v=4",
          "name": "ornicar",
          "url": "https://github.com/ornicar"
        },
        {
          "avatar": "https://avatars.githubusercontent.com/u/402777?s=40&v=4",
          "name": "niklasf",
          "url": "https://github.com/niklasf"
        },
        {
          "avatar": "https://avatars.githubusercontent.com/u/101470903?s=40&v=4",
          "name": "schlawg",
          "url": "https://github.com/schlawg"
        },
        {
          "avatar": "https://avatars.githubusercontent.com/u/19309705?s=40&v=4",
          "name": "benediktwerner",
          "url": "https://github.com/benediktwerner"
        },
        {
          "avatar": "https://avatars.githubusercontent.com/u/56031107?s=40&v=4",
          "name": "kraktus",
          "url": "https://github.com/kraktus"
        }
      ]
    },
    {
      "title": "apache/incubator-gluten",
      "url": "https://github.com/apache/incubator-gluten",
      "description": "Gluten is a middle layer responsible for offloading JVM-based SQL engines' execution to native engines.",
      "language": "Scala",
      "languageColor": "#c22d40",
      "stars": "1,143",
      "forks": "415",
      "addStars": "3",
      "contributors": [
        {
          "avatar": "https://avatars.githubusercontent.com/u/11284395?s=40&v=4",
          "name": "zhztheplayer",
          "url": "https://github.com/zhztheplayer"
        },
        {
          "avatar": "https://avatars.githubusercontent.com/u/13806761?s=40&v=4",
          "name": "PHILO-HE",
          "url": "https://github.com/PHILO-HE"
        },
        {
          "avatar": "https://avatars.githubusercontent.com/u/52736607?s=40&v=4",
          "name": "marin-ma",
          "url": "https://github.com/marin-ma"
        },
        {
          "avatar": "https://avatars.githubusercontent.com/u/41687378?s=40&v=4",
          "name": "rui-mo",
          "url": "https://github.com/rui-mo"
        },
        {
          "avatar": "https://avatars.githubusercontent.com/u/3688732?s=40&v=4",
          "name": "baibaichen",
          "url": "https://github.com/baibaichen"
        }
      ]
    },
    {
      "title": "twitter/the-algorithm",
      "url": "https://github.com/twitter/the-algorithm",
      "description": "Source code for Twitter's Recommendation Algorithm",
      "language": "Scala",
      "languageColor": "#c22d40",
      "stars": "62,049",
      "forks": "12,143",
      "addStars": "7",
      "contributors": [
        {
          "avatar": "https://avatars.githubusercontent.com/u/25687?s=40&v=4",
          "name": "dzhao",
          "url": "https://github.com/dzhao"
        },
        {
          "avatar": "https://avatars.githubusercontent.com/u/20663776?s=40&v=4",
          "name": "pouriya",
          "url": "https://github.com/pouriya"
        },
        {
          "avatar": "https://avatars.githubusercontent.com/u/35087590?s=40&v=4",
          "name": "MrAuro",
          "url": "https://github.com/MrAuro"
        }
      ]
    },
    {
      "title": "apache/spark",
      "url": "https://github.com/apache/spark",
      "description": "Apache Spark - A unified analytics engine for large-scale data processing",
      "language": "Scala",
      "languageColor": "#c22d40",
      "stars": "39,284",
      "forks": "28,194",
      "addStars": "6",
      "contributors": [
        {
          "avatar": "https://avatars.githubusercontent.com/u/6477701?s=40&v=4",
          "name": "HyukjinKwon",
          "url": "https://github.com/HyukjinKwon"
        },
        {
          "avatar": "https://avatars.githubusercontent.com/u/9700541?s=40&v=4",
          "name": "dongjoon-hyun",
          "url": "https://github.com/dongjoon-hyun"
        },
        {
          "avatar": "https://avatars.githubusercontent.com/u/228859?s=40&v=4",
          "name": "mateiz",
          "url": "https://github.com/mateiz"
        },
        {
          "avatar": "https://avatars.githubusercontent.com/u/323388?s=40&v=4",
          "name": "rxin",
          "url": "https://github.com/rxin"
        },
        {
          "avatar": "https://avatars.githubusercontent.com/u/3182036?s=40&v=4",
          "name": "cloud-fan",
          "url": "https://github.com/cloud-fan"
        }
      ]
    },
    {
      "title": "delta-io/delta",
      "url": "https://github.com/delta-io/delta",
      "description": "An open-source storage framework that enables building a Lakehouse architecture with compute engines including Spark, PrestoDB, Flink, Trino, and Hive and APIs",
      "language": "Scala",
      "languageColor": "#c22d40",
      "stars": "7,433",
      "forks": "1,667",
      "addStars": "4",
      "contributors": [
        {
          "avatar": "https://avatars.githubusercontent.com/u/59617782?s=40&v=4",
          "name": "scottsand-db",
          "url": "https://github.com/scottsand-db"
        },
        {
          "avatar": "https://avatars.githubusercontent.com/u/1719945?s=40&v=4",
          "name": "vkorukanti",
          "url": "https://github.com/vkorukanti"
        },
        {
          "avatar": "https://avatars.githubusercontent.com/u/89107911?s=40&v=4",
          "name": "allisonport-db",
          "url": "https://github.com/allisonport-db"
        },
        {
          "avatar": "https://avatars.githubusercontent.com/u/1000778?s=40&v=4",
          "name": "zsxwing",
          "url": "https://github.com/zsxwing"
        },
        {
          "avatar": "https://avatars.githubusercontent.com/u/663212?s=40&v=4",
          "name": "tdas",
          "url": "https://github.com/tdas"
        }
      ]
    },
    {
      "title": "TheHive-Project/TheHive",
      "url": "https://github.com/TheHive-Project/TheHive",
      "description": "TheHive: a Scalable, Open Source and Free Security Incident Response Platform",
      "language": "Scala",
      "languageColor": "#c22d40",
      "stars": "3,363",
      "forks": "614",
      "addStars": "0",
      "contributors": [
        {
          "avatar": "https://avatars.githubusercontent.com/u/23172576?s=40&v=4",
          "name": "To-om",
          "url": "https://github.com/To-om"
        },
        {
          "avatar": "https://avatars.githubusercontent.com/u/21827?s=40&v=4",
          "name": "nadouani",
          "url": "https://github.com/nadouani"
        },
        {
          "avatar": "https://avatars.githubusercontent.com/u/2312874?s=40&v=4",
          "name": "BillOTei",
          "url": "https://github.com/BillOTei"
        },
        {
          "avatar": "https://avatars.githubusercontent.com/u/10635573?s=40&v=4",
          "name": "rriclet",
          "url": "https://github.com/rriclet"
        },
        {
          "avatar": "https://avatars.githubusercontent.com/u/2852427?s=40&v=4",
          "name": "saadkadhi",
          "url": "https://github.com/saadkadhi"
        }
      ]
    },
    {
      "title": "microsoft/SynapseML",
      "url": "https://github.com/microsoft/SynapseML",
      "description": "Simple and Distributed Machine Learning",
      "language": "Scala",
      "languageColor": "#c22d40",
      "stars": "5,042",
      "forks": "830",
      "addStars": "2",
      "contributors": [
        {
          "avatar": "https://avatars.githubusercontent.com/u/6456637?s=40&v=4",
          "name": "mhamilton723",
          "url": "https://github.com/mhamilton723"
        },
        {
          "avatar": "https://avatars.githubusercontent.com/u/82044803?s=40&v=4",
          "name": "serena-ruan",
          "url": "https://github.com/serena-ruan"
        },
        {
          "avatar": "https://avatars.githubusercontent.com/u/24683184?s=40&v=4",
          "name": "imatiach-msft",
          "url": "https://github.com/imatiach-msft"
        },
        {
          "avatar": "https://avatars.githubusercontent.com/u/185905?s=40&v=4",
          "name": "elibarzilay",
          "url": "https://github.com/elibarzilay"
        }
      ]
    },
    {
      "title": "JohnSnowLabs/spark-nlp",
      "url": "https://github.com/JohnSnowLabs/spark-nlp",
      "description": "State of the Art Natural Language Processing",
      "language": "Scala",
      "languageColor": "#c22d40",
      "stars": "3,804",
      "forks": "708",
      "addStars": "0",
      "contributors": [
        {
          "avatar": "https://avatars.githubusercontent.com/u/5762953?s=40&v=4",
          "name": "maziyarpanahi",
          "url": "https://github.com/maziyarpanahi"
        },
        {
          "avatar": "https://avatars.githubusercontent.com/u/69839085?s=40&v=4",
          "name": "murat-gunay",
          "url": "https://github.com/murat-gunay"
        },
        {
          "avatar": "https://avatars.githubusercontent.com/u/69344247?s=40&v=4",
          "name": "gadde5300",
          "url": "https://github.com/gadde5300"
        },
        {
          "avatar": "https://avatars.githubusercontent.com/u/27952699?s=40&v=4",
          "name": "saif-ellafi",
          "url": "https://github.com/saif-ellafi"
        },
        {
          "avatar": "https://avatars.githubusercontent.com/u/33089471?s=40&v=4",
          "name": "DevinTDHa",
          "url": "https://github.com/DevinTDHa"
        }
      ]
    },
    {
      "title": "broadinstitute/cromwell",
      "url": "https://github.com/broadinstitute/cromwell",
      "description": "Scientific workflow engine designed for simplicity & scalability. Trivially transition between one off use cases to massive scale production environments",
      "language": "Scala",
      "languageColor": "#c22d40",
      "stars": "987",
      "forks": "358",
      "addStars": "0",
      "contributors": [
        {
          "avatar": "https://avatars.githubusercontent.com/u/13006282?s=40&v=4",
          "name": "cjllanwarne",
          "url": "https://github.com/cjllanwarne"
        },
        {
          "avatar": "https://avatars.githubusercontent.com/u/791985?s=40&v=4",
          "name": "kshakir",
          "url": "https://github.com/kshakir"
        },
        {
          "avatar": "https://avatars.githubusercontent.com/u/10790523?s=40&v=4",
          "name": "mcovarr",
          "url": "https://github.com/mcovarr"
        },
        {
          "avatar": "https://avatars.githubusercontent.com/u/2978948?s=40&v=4",
          "name": "Horneth",
          "url": "https://github.com/Horneth"
        },
        {
          "avatar": "https://avatars.githubusercontent.com/u/961771?s=40&v=4",
          "name": "geoffjentry",
          "url": "https://github.com/geoffjentry"
        }
      ]
    },
    {
      "title": "crealytics/spark-excel",
      "url": "https://github.com/crealytics/spark-excel",
      "description": "A Spark plugin for reading and writing Excel files",
      "language": "Scala",
      "languageColor": "#c22d40",
      "stars": "460",
      "forks": "147",
      "addStars": "2",
      "contributors": [
        {
          "avatar": "https://avatars.githubusercontent.com/u/43047562?s=40&v=4",
          "name": "scala-steward",
          "url": "https://github.com/scala-steward"
        },
        {
          "avatar": "https://avatars.githubusercontent.com/u/35170?s=40&v=4",
          "name": "nightscape",
          "url": "https://github.com/nightscape"
        },
        {
          "avatar": "https://avatars.githubusercontent.com/u/11783444?s=40&v=4",
          "name": "pjfanning",
          "url": "https://github.com/pjfanning"
        },
        {
          "avatar": "https://avatars.githubusercontent.com/u/9248764?s=40&v=4",
          "name": "EnverOsmanov",
          "url": "https://github.com/EnverOsmanov"
        }
      ]
    },
    {
      "title": "sbt/sbt",
      "url": "https://github.com/sbt/sbt",
      "description": "sbt, the interactive build tool",
      "language": "Scala",
      "languageColor": "#c22d40",
      "stars": "4,788",
      "forks": "931",
      "addStars": "1",
      "contributors": [
        {
          "avatar": "https://avatars.githubusercontent.com/u/184683?s=40&v=4",
          "name": "eed3si9n",
          "url": "https://github.com/eed3si9n"
        },
        {
          "avatar": "https://avatars.githubusercontent.com/u/72742?s=40&v=4",
          "name": "harrah",
          "url": "https://github.com/harrah"
        },
        {
          "avatar": "https://avatars.githubusercontent.com/u/2658825?s=40&v=4",
          "name": "eatkins",
          "url": "https://github.com/eatkins"
        },
        {
          "avatar": "https://avatars.githubusercontent.com/u/344610?s=40&v=4",
          "name": "dwijnand",
          "url": "https://github.com/dwijnand"
        },
        {
          "avatar": "https://avatars.githubusercontent.com/u/29006?s=40&v=4",
          "name": "jsuereth",
          "url": "https://github.com/jsuereth"
        }
      ]
    },
    {
      "title": "apache/kyuubi",
      "url": "https://github.com/apache/kyuubi",
      "description": "Apache Kyuubi is a distributed and multi-tenant gateway to provide serverless SQL on data warehouses and lakehouses.",
      "language": "Scala",
      "languageColor": "#c22d40",
      "stars": "2,068",
      "forks": "903",
      "addStars": "3",
      "contributors": [
        {
          "avatar": "https://avatars.githubusercontent.com/u/8326978?s=40&v=4",
          "name": "yaooqinn",
          "url": "https://github.com/yaooqinn"
        },
        {
          "avatar": "https://avatars.githubusercontent.com/u/26535726?s=40&v=4",
          "name": "pan3793",
          "url": "https://github.com/pan3793"
        },
        {
          "avatar": "https://avatars.githubusercontent.com/u/6757692?s=40&v=4",
          "name": "turboFei",
          "url": "https://github.com/turboFei"
        },
        {
          "avatar": "https://avatars.githubusercontent.com/u/1935105?s=40&v=4",
          "name": "bowenliang123",
          "url": "https://github.com/bowenliang123"
        },
        {
          "avatar": "https://avatars.githubusercontent.com/u/12025282?s=40&v=4",
          "name": "ulysses-you",
          "url": "https://github.com/ulysses-you"
        }
      ]
    },
    {
      "title": "delta-io/delta-sharing",
      "url": "https://github.com/delta-io/delta-sharing",
      "description": "An open protocol for secure data sharing",
      "language": "Scala",
      "languageColor": "#c22d40",
      "stars": "744",
      "forks": "168",
      "addStars": "0",
      "contributors": [
        {
          "avatar": "https://avatars.githubusercontent.com/u/87341375?s=40&v=4",
          "name": "linzhou-db",
          "url": "https://github.com/linzhou-db"
        },
        {
          "avatar": "https://avatars.githubusercontent.com/u/1000778?s=40&v=4",
          "name": "zsxwing",
          "url": "https://github.com/zsxwing"
        },
        {
          "avatar": "https://avatars.githubusercontent.com/u/98838463?s=40&v=4",
          "name": "chakankardb",
          "url": "https://github.com/chakankardb"
        },
        {
          "avatar": "https://avatars.githubusercontent.com/u/170376607?s=40&v=4",
          "name": "pranavsuku-db",
          "url": "https://github.com/pranavsuku-db"
        },
        {
          "avatar": "https://avatars.githubusercontent.com/u/12293805?s=40&v=4",
          "name": "zhuansunxt",
          "url": "https://github.com/zhuansunxt"
        }
      ]
    },
    {
      "title": "Netflix/atlas",
      "url": "https://github.com/Netflix/atlas",
      "description": "In-memory dimensional time series database.",
      "language": "Scala",
      "languageColor": "#c22d40",
      "stars": "3,431",
      "forks": "301",
      "addStars": "1",
      "contributors": [
        {
          "avatar": "https://avatars.githubusercontent.com/u/1289028?s=40&v=4",
          "name": "brharrington",
          "url": "https://github.com/brharrington"
        },
        {
          "avatar": "https://avatars.githubusercontent.com/u/1302547?s=40&v=4",
          "name": "jfz",
          "url": "https://github.com/jfz"
        },
        {
          "avatar": "https://avatars.githubusercontent.com/u/794729?s=40&v=4",
          "name": "zimmermatt",
          "url": "https://github.com/zimmermatt"
        },
        {
          "avatar": "https://avatars.githubusercontent.com/u/1377700?s=40&v=4",
          "name": "manolama",
          "url": "https://github.com/manolama"
        },
        {
          "avatar": "https://avatars.githubusercontent.com/u/1192501?s=40&v=4",
          "name": "copperlight",
          "url": "https://github.com/copperlight"
        }
      ]
    },
    {
      "title": "awslabs/deequ",
      "url": "https://github.com/awslabs/deequ",
      "description": "Deequ is a library built on top of Apache Spark for defining \"unit tests for data\", which measure data quality in large datasets.",
      "language": "Scala",
      "languageColor": "#c22d40",
      "stars": "3,251",
      "forks": "532",
      "addStars": "5",
      "contributors": [
        {
          "avatar": "https://avatars.githubusercontent.com/u/409707?s=40&v=4",
          "name": "sscdotopen",
          "url": "https://github.com/sscdotopen"
        },
        {
          "avatar": "https://avatars.githubusercontent.com/u/65777064?s=40&v=4",
          "name": "rdsharma26",
          "url": "https://github.com/rdsharma26"
        },
        {
          "avatar": "https://avatars.githubusercontent.com/u/8267636?s=40&v=4",
          "name": "tdhd",
          "url": "https://github.com/tdhd"
        },
        {
          "avatar": "https://avatars.githubusercontent.com/u/38978338?s=40&v=4",
          "name": "twollnik",
          "url": "https://github.com/twollnik"
        },
        {
          "avatar": "https://avatars.githubusercontent.com/u/114528615?s=40&v=4",
          "name": "eycho-am",
          "url": "https://github.com/eycho-am"
        }
      ]
    },
    {
      "title": "microsoft/sql-spark-connector",
      "url": "https://github.com/microsoft/sql-spark-connector",
      "description": "Apache Spark Connector for SQL Server and Azure SQL",
      "language": "Scala",
      "languageColor": "#c22d40",
      "stars": "274",
      "forks": "116",
      "addStars": "0",
      "contributors": [
        {
          "avatar": "https://avatars.githubusercontent.com/u/22081978?s=40&v=4",
          "name": "rajmera3",
          "url": "https://github.com/rajmera3"
        },
        {
          "avatar": "https://avatars.githubusercontent.com/u/1579057?s=40&v=4",
          "name": "shivsood",
          "url": "https://github.com/shivsood"
        },
        {
          "avatar": "https://avatars.githubusercontent.com/u/68044595?s=40&v=4",
          "name": "luxu1-ms",
          "url": "https://github.com/luxu1-ms"
        },
        {
          "avatar": "https://avatars.githubusercontent.com/u/743743?s=40&v=4",
          "name": "DaniBunny",
          "url": "https://github.com/DaniBunny"
        },
        {
          "avatar": "https://avatars.githubusercontent.com/u/16342666?s=40&v=4",
          "name": "arvindshmicrosoft",
          "url": "https://github.com/arvindshmicrosoft"
        }
      ]
    },
    {
      "title": "gatling/gatling",
      "url": "https://github.com/gatling/gatling",
      "description": "Modern Load Testing as Code",
      "language": "Scala",
      "languageColor": "#c22d40",
      "stars": "6,400",
      "forks": "1,189",
      "addStars": "0",
      "contributors": [
        {
          "avatar": "https://avatars.githubusercontent.com/u/849197?s=40&v=4",
          "name": "slandelle",
          "url": "https://github.com/slandelle"
        },
        {
          "avatar": "https://avatars.githubusercontent.com/u/1514127?s=40&v=4",
          "name": "pdalpra",
          "url": "https://github.com/pdalpra"
        },
        {
          "avatar": "https://avatars.githubusercontent.com/u/294333?s=40&v=4",
          "name": "rsertelon",
          "url": "https://github.com/rsertelon"
        },
        {
          "avatar": "https://avatars.githubusercontent.com/u/600102?s=40&v=4",
          "name": "nremond",
          "url": "https://github.com/nremond"
        }
      ]
    },
    {
      "title": "chipsalliance/chisel",
      "url": "https://github.com/chipsalliance/chisel",
      "description": "Chisel: A Modern Hardware Design Language",
      "language": "Scala",
      "languageColor": "#c22d40",
      "stars": "3,912",
      "forks": "588",
      "addStars": "2",
      "contributors": [
        {
          "avatar": "https://avatars.githubusercontent.com/u/8584418?s=40&v=4",
          "name": "jackkoenig",
          "url": "https://github.com/jackkoenig"
        },
        {
          "avatar": "https://avatars.githubusercontent.com/u/1018530?s=40&v=4",
          "name": "seldridge",
          "url": "https://github.com/seldridge"
        },
        {
          "avatar": "https://avatars.githubusercontent.com/u/6845888?s=40&v=4",
          "name": "ucbjrl",
          "url": "https://github.com/ucbjrl"
        }
      ]
    },
    {
      "title": "rtyley/bfg-repo-cleaner",
      "url": "https://github.com/rtyley/bfg-repo-cleaner",
      "description": "Removes large or troublesome blobs like git-filter-branch does, but faster. And written in Scala",
      "language": "Scala",
      "languageColor": "#c22d40",
      "stars": "11,004",
      "forks": "547",
      "addStars": "7",
      "contributors": [
        {
          "avatar": "https://avatars.githubusercontent.com/u/52038?s=40&v=4",
          "name": "rtyley",
          "url": "https://github.com/rtyley"
        },
        {
          "avatar": "https://avatars.githubusercontent.com/u/1103477?s=40&v=4",
          "name": "javabrett",
          "url": "https://github.com/javabrett"
        },
        {
          "avatar": "https://avatars.githubusercontent.com/u/344610?s=40&v=4",
          "name": "dwijnand",
          "url": "https://github.com/dwijnand"
        },
        {
          "avatar": "https://avatars.githubusercontent.com/u/14003?s=40&v=4",
          "name": "alecthegeek",
          "url": "https://github.com/alecthegeek"
        },
        {
          "avatar": "https://avatars.githubusercontent.com/u/1146876?s=40&v=4",
          "name": "kevinji",
          "url": "https://github.com/kevinji"
        }
      ]
    }
  ]
}