{
  "title": "GitHub Java Languages Monthly Trending",
  "description": "Monthly Trending of Java Languages in GitHub",
  "link": "https://github.com/isboyjc/github-trending-api",
  "pubDate": "Sun, 18 May 2025 02:47:12 GMT",
  "items": [
    {
      "title": "alibaba/spring-ai-alibaba",
      "url": "https://github.com/alibaba/spring-ai-alibaba",
      "description": "Agentic AI Framework for Java Developers",
      "language": "Java",
      "languageColor": "#b07219",
      "stars": "3,341",
      "forks": "619",
      "addStars": "1,032",
      "contributors": [
        {
          "avatar": "https://avatars.githubusercontent.com/u/18097545?s=40&v=4",
          "name": "chickenlj",
          "url": "https://github.com/chickenlj"
        },
        {
          "avatar": "https://avatars.githubusercontent.com/u/77964041?s=40&v=4",
          "name": "yuluo-yx",
          "url": "https://github.com/yuluo-yx"
        },
        {
          "avatar": "https://avatars.githubusercontent.com/u/173772258?s=40&v=4",
          "name": "answeropensource",
          "url": "https://github.com/answeropensource"
        },
        {
          "avatar": "https://avatars.githubusercontent.com/u/76430175?s=40&v=4",
          "name": "brianxiadong",
          "url": "https://github.com/brianxiadong"
        },
        {
          "avatar": "https://avatars.githubusercontent.com/u/29418975?s=40&v=4",
          "name": "zhangshenghang",
          "url": "https://github.com/zhangshenghang"
        }
      ]
    },
    {
      "title": "Stirling-Tools/Stirling-PDF",
      "url": "https://github.com/Stirling-Tools/Stirling-PDF",
      "description": "#1 Locally hosted web application that allows you to perform various operations on PDF files",
      "language": "Java",
      "languageColor": "#b07219",
      "stars": "59,110",
      "forks": "4,951",
      "addStars": "3,167",
      "contributors": [
        {
          "avatar": "https://avatars.githubusercontent.com/u/77850077?s=40&v=4",
          "name": "Frooodle",
          "url": "https://github.com/Frooodle"
        },
        {
          "avatar": "https://avatars.githubusercontent.com/u/4592558?s=40&v=4",
          "name": "Ludy87",
          "url": "https://github.com/Ludy87"
        }
      ]
    },
    {
      "title": "TeamNewPipe/NewPipe",
      "url": "https://github.com/TeamNewPipe/NewPipe",
      "description": "A libre lightweight streaming front-end for Android.",
      "language": "Java",
      "languageColor": "#b07219",
      "stars": "33,857",
      "forks": "3,194",
      "addStars": "421",
      "contributors": [
        {
          "avatar": "https://avatars.githubusercontent.com/u/36421898?s=40&v=4",
          "name": "Stypox",
          "url": "https://github.com/Stypox"
        },
        {
          "avatar": "https://avatars.githubusercontent.com/u/17365767?s=40&v=4",
          "name": "TobiGr",
          "url": "https://github.com/TobiGr"
        },
        {
          "avatar": "https://avatars.githubusercontent.com/u/1891273?s=40&v=4",
          "name": "theScrabi",
          "url": "https://github.com/theScrabi"
        },
        {
          "avatar": "https://avatars.githubusercontent.com/u/1607653?s=40&v=4",
          "name": "weblate",
          "url": "https://github.com/weblate"
        },
        {
          "avatar": "https://avatars.githubusercontent.com/u/40789489?s=40&v=4",
          "name": "litetex",
          "url": "https://github.com/litetex"
        }
      ]
    },
    {
      "title": "AutoMQ/automq",
      "url": "https://github.com/AutoMQ/automq",
      "description": "AutoMQ is a stateless Kafka on S3. 10x Cost-Effective. No Cross-AZ Traffic Cost. Autoscale in seconds. Single-digit ms latency. Multi-AZ Availability.",
      "language": "Java",
      "languageColor": "#b07219",
      "stars": "6,380",
      "forks": "431",
      "addStars": "997",
      "contributors": [
        {
          "avatar": "https://avatars.githubusercontent.com/u/24747?s=40&v=4",
          "name": "ijuma",
          "url": "https://github.com/ijuma"
        },
        {
          "avatar": "https://avatars.githubusercontent.com/u/8959638?s=40&v=4",
          "name": "mjsax",
          "url": "https://github.com/mjsax"
        },
        {
          "avatar": "https://avatars.githubusercontent.com/u/5719209?s=40&v=4",
          "name": "superhx",
          "url": "https://github.com/superhx"
        },
        {
          "avatar": "https://avatars.githubusercontent.com/u/10729597?s=40&v=4",
          "name": "guozhangwang",
          "url": "https://github.com/guozhangwang"
        },
        {
          "avatar": "https://avatars.githubusercontent.com/u/20128924?s=40&v=4",
          "name": "SCNieh",
          "url": "https://github.com/SCNieh"
        }
      ]
    },
    {
      "title": "spring-projects/spring-ai",
      "url": "https://github.com/spring-projects/spring-ai",
      "description": "An Application Framework for AI Engineering",
      "language": "Java",
      "languageColor": "#b07219",
      "stars": "5,143",
      "forks": "1,419",
      "addStars": "467",
      "contributors": [
        {
          "avatar": "https://avatars.githubusercontent.com/u/1351573?s=40&v=4",
          "name": "tzolov",
          "url": "https://github.com/tzolov"
        },
        {
          "avatar": "https://avatars.githubusercontent.com/u/247466?s=40&v=4",
          "name": "markpollack",
          "url": "https://github.com/markpollack"
        },
        {
          "avatar": "https://avatars.githubusercontent.com/u/151690?s=40&v=4",
          "name": "ilayaperumalg",
          "url": "https://github.com/ilayaperumalg"
        },
        {
          "avatar": "https://avatars.githubusercontent.com/u/827682?s=40&v=4",
          "name": "sobychacko",
          "url": "https://github.com/sobychacko"
        },
        {
          "avatar": "https://avatars.githubusercontent.com/u/8523418?s=40&v=4",
          "name": "ThomasVitale",
          "url": "https://github.com/ThomasVitale"
        }
      ]
    },
    {
      "title": "Anuken/Mindustry",
      "url": "https://github.com/Anuken/Mindustry",
      "description": "The automation tower defense RTS",
      "language": "Java",
      "languageColor": "#b07219",
      "stars": "23,922",
      "forks": "3,102",
      "addStars": "321",
      "contributors": [
        {
          "avatar": "https://avatars.githubusercontent.com/u/10100000?s=40&v=4",
          "name": "Anuken",
          "url": "https://github.com/Anuken"
        },
        {
          "avatar": "https://avatars.githubusercontent.com/u/3179271?s=40&v=4",
          "name": "Quezler",
          "url": "https://github.com/Quezler"
        },
        {
          "avatar": "https://avatars.githubusercontent.com/u/54301439?s=40&v=4",
          "name": "MEEPofFaith",
          "url": "https://github.com/MEEPofFaith"
        },
        {
          "avatar": "https://avatars.githubusercontent.com/u/2945013?s=40&v=4",
          "name": "Epowerj",
          "url": "https://github.com/Epowerj"
        },
        {
          "avatar": "https://avatars.githubusercontent.com/u/31485341?s=40&v=4",
          "name": "Prosta4okua",
          "url": "https://github.com/Prosta4okua"
        }
      ]
    },
    {
      "title": "termux/termux-app",
      "url": "https://github.com/termux/termux-app",
      "description": "Termux - a terminal emulator application for Android OS extendible by variety of packages.",
      "language": "Java",
      "languageColor": "#b07219",
      "stars": "41,381",
      "forks": "4,481",
      "addStars": "874",
      "contributors": [
        {
          "avatar": "https://avatars.githubusercontent.com/u/31106828?s=40&v=4",
          "name": "agnostic-apollo",
          "url": "https://github.com/agnostic-apollo"
        },
        {
          "avatar": "https://avatars.githubusercontent.com/u/277251?s=40&v=4",
          "name": "fornwall",
          "url": "https://github.com/fornwall"
        },
        {
          "avatar": "https://avatars.githubusercontent.com/u/18900601?s=40&v=4",
          "name": "Grimler91",
          "url": "https://github.com/Grimler91"
        },
        {
          "avatar": "https://avatars.githubusercontent.com/u/3536343?s=40&v=4",
          "name": "maoabc",
          "url": "https://github.com/maoabc"
        },
        {
          "avatar": "https://avatars.githubusercontent.com/u/601966?s=40&v=4",
          "name": "trygveaa",
          "url": "https://github.com/trygveaa"
        }
      ]
    },
    {
      "title": "iluwatar/java-design-patterns",
      "url": "https://github.com/iluwatar/java-design-patterns",
      "description": "Design patterns implemented in Java",
      "language": "Java",
      "languageColor": "#b07219",
      "stars": "91,765",
      "forks": "26,978",
      "addStars": "540",
      "contributors": [
        {
          "avatar": "https://avatars.githubusercontent.com/u/582346?s=40&v=4",
          "name": "iluwatar",
          "url": "https://github.com/iluwatar"
        },
        {
          "avatar": "https://avatars.githubusercontent.com/u/1792515?s=40&v=4",
          "name": "npathai",
          "url": "https://github.com/npathai"
        },
        {
          "avatar": "https://avatars.githubusercontent.com/u/13291222?s=40&v=4",
          "name": "ohbus",
          "url": "https://github.com/ohbus"
        }
      ]
    },
    {
      "title": "questdb/questdb",
      "url": "https://github.com/questdb/questdb",
      "description": "QuestDB is a high performance, open-source, time-series database",
      "language": "Java",
      "languageColor": "#b07219",
      "stars": "15,201",
      "forks": "1,238",
      "addStars": "144",
      "contributors": [
        {
          "avatar": "https://avatars.githubusercontent.com/u/7276403?s=40&v=4",
          "name": "bluestreak01",
          "url": "https://github.com/bluestreak01"
        },
        {
          "avatar": "https://avatars.githubusercontent.com/u/2159629?s=40&v=4",
          "name": "ideoma",
          "url": "https://github.com/ideoma"
        },
        {
          "avatar": "https://avatars.githubusercontent.com/u/37772591?s=40&v=4",
          "name": "puzpuzpuz",
          "url": "https://github.com/puzpuzpuz"
        },
        {
          "avatar": "https://avatars.githubusercontent.com/u/158619?s=40&v=4",
          "name": "jerrinot",
          "url": "https://github.com/jerrinot"
        },
        {
          "avatar": "https://avatars.githubusercontent.com/u/26925920?s=40&v=4",
          "name": "bziobrowski",
          "url": "https://github.com/bziobrowski"
        }
      ]
    },
    {
      "title": "spring-projects/spring-boot",
      "url": "https://github.com/spring-projects/spring-boot",
      "description": "Spring Boot helps you to create Spring-powered, production-grade applications and services with absolute minimum fuss.",
      "language": "Java",
      "languageColor": "#b07219",
      "stars": "77,144",
      "forks": "41,176",
      "addStars": "421",
      "contributors": [
        {
          "avatar": "https://avatars.githubusercontent.com/u/914682?s=40&v=4",
          "name": "wilkinsona",
          "url": "https://github.com/wilkinsona"
        },
        {
          "avatar": "https://avatars.githubusercontent.com/u/490484?s=40&v=4",
          "name": "snicoll",
          "url": "https://github.com/snicoll"
        },
        {
          "avatar": "https://avatars.githubusercontent.com/u/519772?s=40&v=4",
          "name": "philwebb",
          "url": "https://github.com/philwebb"
        },
        {
          "avatar": "https://avatars.githubusercontent.com/u/98899556?s=40&v=4",
          "name": "mhalbritter",
          "url": "https://github.com/mhalbritter"
        },
        {
          "avatar": "https://avatars.githubusercontent.com/u/1761408?s=40&v=4",
          "name": "mbhave",
          "url": "https://github.com/mbhave"
        }
      ]
    },
    {
      "title": "LawnchairLauncher/lawnchair",
      "url": "https://github.com/LawnchairLauncher/lawnchair",
      "description": "No clever tagline needed.",
      "language": "Java",
      "languageColor": "#b07219",
      "stars": "10,260",
      "forks": "1,292",
      "addStars": "184",
      "contributors": [
        {
          "avatar": "https://avatars.githubusercontent.com/u/440407?s=40&v=4",
          "name": "mikejurka",
          "url": "https://github.com/mikejurka"
        },
        {
          "avatar": "https://avatars.githubusercontent.com/u/29541356?s=40&v=4",
          "name": "alexchau-google",
          "url": "https://github.com/alexchau-google"
        },
        {
          "avatar": "https://avatars.githubusercontent.com/u/1196024?s=40&v=4",
          "name": "vinitnayak7",
          "url": "https://github.com/vinitnayak7"
        },
        {
          "avatar": "https://avatars.githubusercontent.com/u/112512443?s=40&v=4",
          "name": "sfufagoogle",
          "url": "https://github.com/sfufagoogle"
        },
        {
          "avatar": "https://avatars.githubusercontent.com/u/68665119?s=40&v=4",
          "name": "stevenckngaa",
          "url": "https://github.com/stevenckngaa"
        }
      ]
    },
    {
      "title": "conductor-oss/conductor",
      "url": "https://github.com/conductor-oss/conductor",
      "description": "Conductor is an event driven orchestration platform providing durable and highly resilient execution engine for your applications",
      "language": "Java",
      "languageColor": "#b07219",
      "stars": "22,237",
      "forks": "600",
      "addStars": "1,998",
      "contributors": [
        {
          "avatar": "https://avatars.githubusercontent.com/u/202610049?s=40&v=4",
          "name": "orkes-harshil",
          "url": "https://github.com/orkes-harshil"
        },
        {
          "avatar": "https://avatars.githubusercontent.com/u/2246128?s=40&v=4",
          "name": "v1r3n",
          "url": "https://github.com/v1r3n"
        },
        {
          "avatar": "https://avatars.githubusercontent.com/u/4755315?s=40&v=4",
          "name": "jmigueprieto",
          "url": "https://github.com/jmigueprieto"
        },
        {
          "avatar": "https://avatars.githubusercontent.com/u/13348474?s=40&v=4",
          "name": "c4lm",
          "url": "https://github.com/c4lm"
        },
        {
          "avatar": "https://avatars.githubusercontent.com/u/5434244?s=40&v=4",
          "name": "Robban1980",
          "url": "https://github.com/Robban1980"
        }
      ]
    },
    {
      "title": "libgdx/libgdx",
      "url": "https://github.com/libgdx/libgdx",
      "description": "Desktop/Android/HTML5/iOS Java game development framework",
      "language": "Java",
      "languageColor": "#b07219",
      "stars": "24,033",
      "forks": "6,495",
      "addStars": "139",
      "contributors": [
        {
          "avatar": "https://avatars.githubusercontent.com/u/434010?s=40&v=4",
          "name": "NathanSweet",
          "url": "https://github.com/NathanSweet"
        },
        {
          "avatar": "https://avatars.githubusercontent.com/u/514052?s=40&v=4",
          "name": "badlogic",
          "url": "https://github.com/badlogic"
        },
        {
          "avatar": "https://avatars.githubusercontent.com/u/2349087?s=40&v=4",
          "name": "xoppa",
          "url": "https://github.com/xoppa"
        },
        {
          "avatar": "https://avatars.githubusercontent.com/u/1095464?s=40&v=4",
          "name": "MobiDevelop",
          "url": "https://github.com/MobiDevelop"
        },
        {
          "avatar": "https://avatars.githubusercontent.com/u/4346114?s=40&v=4",
          "name": "Tom-Ski",
          "url": "https://github.com/Tom-Ski"
        }
      ]
    },
    {
      "title": "quarkusio/quarkus",
      "url": "https://github.com/quarkusio/quarkus",
      "description": "Quarkus: Supersonic Subatomic Java.",
      "language": "Java",
      "languageColor": "#b07219",
      "stars": "14,517",
      "forks": "2,843",
      "addStars": "212",
      "contributors": [
        {
          "avatar": "https://avatars.githubusercontent.com/u/1279749?s=40&v=4",
          "name": "gsmet",
          "url": "https://github.com/gsmet"
        },
        {
          "avatar": "https://avatars.githubusercontent.com/u/4374975?s=40&v=4",
          "name": "geoand",
          "url": "https://github.com/geoand"
        },
        {
          "avatar": "https://avatars.githubusercontent.com/u/328571?s=40&v=4",
          "name": "stuartwdouglas",
          "url": "https://github.com/stuartwdouglas"
        },
        {
          "avatar": "https://avatars.githubusercontent.com/u/54133?s=40&v=4",
          "name": "gastaldi",
          "url": "https://github.com/gastaldi"
        }
      ]
    },
    {
      "title": "halo-dev/halo",
      "url": "https://github.com/halo-dev/halo",
      "description": "强大易用的开源建站工具。",
      "language": "Java",
      "languageColor": "#b07219",
      "stars": "35,572",
      "forks": "9,905",
      "addStars": "393",
      "contributors": [
        {
          "avatar": "https://avatars.githubusercontent.com/u/21301288?s=40&v=4",
          "name": "ruibaby",
          "url": "https://github.com/ruibaby"
        },
        {
          "avatar": "https://avatars.githubusercontent.com/u/16865714?s=40&v=4",
          "name": "JohnNiang",
          "url": "https://github.com/JohnNiang"
        },
        {
          "avatar": "https://avatars.githubusercontent.com/u/38999863?s=40&v=4",
          "name": "guqing",
          "url": "https://github.com/guqing"
        },
        {
          "avatar": "https://avatars.githubusercontent.com/u/31335418?s=40&v=4",
          "name": "LIlGG",
          "url": "https://github.com/LIlGG"
        }
      ]
    },
    {
      "title": "keycloak/keycloak",
      "url": "https://github.com/keycloak/keycloak",
      "description": "Open Source Identity and Access Management For Modern Applications and Services",
      "language": "Java",
      "languageColor": "#b07219",
      "stars": "27,234",
      "forks": "7,301",
      "addStars": "609",
      "contributors": [
        {
          "avatar": "https://avatars.githubusercontent.com/u/2271511?s=40&v=4",
          "name": "stianst",
          "url": "https://github.com/stianst"
        },
        {
          "avatar": "https://avatars.githubusercontent.com/u/704239?s=40&v=4",
          "name": "patriot1burke",
          "url": "https://github.com/patriot1burke"
        },
        {
          "avatar": "https://avatars.githubusercontent.com/u/1223965?s=40&v=4",
          "name": "mposolda",
          "url": "https://github.com/mposolda"
        },
        {
          "avatar": "https://avatars.githubusercontent.com/u/51133?s=40&v=4",
          "name": "edewit",
          "url": "https://github.com/edewit"
        }
      ]
    },
    {
      "title": "yuliskov/SmartTube",
      "url": "https://github.com/yuliskov/SmartTube",
      "description": "Advanced player for set-top boxes and tvs running Android OS",
      "language": "Java",
      "languageColor": "#b07219",
      "stars": "22,694",
      "forks": "1,213",
      "addStars": "483",
      "contributors": [
        {
          "avatar": "https://avatars.githubusercontent.com/u/5897464?s=40&v=4",
          "name": "yuliskov",
          "url": "https://github.com/yuliskov"
        },
        {
          "avatar": "https://avatars.githubusercontent.com/u/74490408?s=40&v=4",
          "name": "mpama2016",
          "url": "https://github.com/mpama2016"
        },
        {
          "avatar": "https://avatars.githubusercontent.com/u/32204990?s=40&v=4",
          "name": "Resshi",
          "url": "https://github.com/Resshi"
        },
        {
          "avatar": "https://avatars.githubusercontent.com/u/59088697?s=40&v=4",
          "name": "foreveryoungforty",
          "url": "https://github.com/foreveryoungforty"
        },
        {
          "avatar": "https://avatars.githubusercontent.com/u/41143572?s=40&v=4",
          "name": "mapi68",
          "url": "https://github.com/mapi68"
        }
      ]
    },
    {
      "title": "dromara/Sa-Token",
      "url": "https://github.com/dromara/Sa-Token",
      "description": "一个轻量级 Java 权限认证框架，让鉴权变得简单、优雅！—— 登录认证、权限认证、分布式Session会话、微服务网关鉴权、单点登录、OAuth2.0",
      "language": "Java",
      "languageColor": "#b07219",
      "stars": "17,646",
      "forks": "2,740",
      "addStars": "295",
      "contributors": [
        {
          "avatar": "https://avatars.githubusercontent.com/u/36243476?s=40&v=4",
          "name": "click33",
          "url": "https://github.com/click33"
        },
        {
          "avatar": "https://avatars.githubusercontent.com/u/2993611?s=40&v=4",
          "name": "noear",
          "url": "https://github.com/noear"
        },
        {
          "avatar": "https://avatars.githubusercontent.com/u/40094040?s=40&v=4",
          "name": "AppleOfGray",
          "url": "https://github.com/AppleOfGray"
        }
      ]
    },
    {
      "title": "alibaba/nacos",
      "url": "https://github.com/alibaba/nacos",
      "description": "an easy-to-use dynamic service discovery, configuration and service management platform for building cloud native applications.",
      "language": "Java",
      "languageColor": "#b07219",
      "stars": "31,387",
      "forks": "13,021",
      "addStars": "242",
      "contributors": [
        {
          "avatar": "https://avatars.githubusercontent.com/u/37170243?s=40&v=4",
          "name": "KomachiSion",
          "url": "https://github.com/KomachiSion"
        },
        {
          "avatar": "https://avatars.githubusercontent.com/u/4593375?s=40&v=4",
          "name": "nkorange",
          "url": "https://github.com/nkorange"
        },
        {
          "avatar": "https://avatars.githubusercontent.com/u/23445172?s=40&v=4",
          "name": "chuntaojun",
          "url": "https://github.com/chuntaojun"
        },
        {
          "avatar": "https://avatars.githubusercontent.com/u/10842824?s=40&v=4",
          "name": "loadchange",
          "url": "https://github.com/loadchange"
        },
        {
          "avatar": "https://avatars.githubusercontent.com/u/20452676?s=40&v=4",
          "name": "shiyiyue1102",
          "url": "https://github.com/shiyiyue1102"
        }
      ]
    },
    {
      "title": "hkhcoder/vprofile-project",
      "url": "https://github.com/hkhcoder/vprofile-project",
      "description": "",
      "language": "Java",
      "languageColor": "#b07219",
      "stars": "611",
      "forks": "2,888",
      "addStars": "76",
      "contributors": [
        {
          "avatar": "https://avatars.githubusercontent.com/u/137309866?s=40&v=4",
          "name": "hkhcoder",
          "url": "https://github.com/hkhcoder"
        },
        {
          "avatar": "https://avatars.githubusercontent.com/u/46835275?s=40&v=4",
          "name": "devopshydclub",
          "url": "https://github.com/devopshydclub"
        },
        {
          "avatar": "https://avatars.githubusercontent.com/u/147797447?s=40&v=4",
          "name": "devops4sure",
          "url": "https://github.com/devops4sure"
        }
      ]
    },
    {
      "title": "skylot/jadx",
      "url": "https://github.com/skylot/jadx",
      "description": "Dex to Java decompiler",
      "language": "Java",
      "languageColor": "#b07219",
      "stars": "43,995",
      "forks": "5,070",
      "addStars": "428",
      "contributors": [
        {
          "avatar": "https://avatars.githubusercontent.com/u/118523?s=40&v=4",
          "name": "skylot",
          "url": "https://github.com/skylot"
        },
        {
          "avatar": "https://avatars.githubusercontent.com/u/924885?s=40&v=4",
          "name": "jpstotz",
          "url": "https://github.com/jpstotz"
        },
        {
          "avatar": "https://avatars.githubusercontent.com/u/2410127?s=40&v=4",
          "name": "asashour",
          "url": "https://github.com/asashour"
        },
        {
          "avatar": "https://avatars.githubusercontent.com/u/58364572?s=40&v=4",
          "name": "nitram84",
          "url": "https://github.com/nitram84"
        },
        {
          "avatar": "https://avatars.githubusercontent.com/u/15173437?s=40&v=4",
          "name": "bagipro",
          "url": "https://github.com/bagipro"
        }
      ]
    },
    {
      "title": "CarGuo/GSYVideoPlayer",
      "url": "https://github.com/CarGuo/GSYVideoPlayer",
      "description": "视频播放器（IJKplayer、ExoPlayer、MediaPlayer），HTTPS，16k page size，支持弹幕，外挂字幕，支持滤镜、水印、gif截图，片头广告、中间广告，多个同时播放，支持基本的拖动，声音、亮度调节，支持边播边缓存，支持视频自带rotation的旋转（90,270之类），重力旋转与手动旋转的同步支持，支持列表播放 ，列表全屏动画，视频加载速度，列表小窗口支持拖动，动画效果，调整比例，多分辨率切换，支持切换播放器，进度条小窗口预览，列表切换详情页面无缝播放，rtsp、concat、mpeg。",
      "language": "Java",
      "languageColor": "#b07219",
      "stars": "20,789",
      "forks": "4,263",
      "addStars": "111",
      "contributors": [
        {
          "avatar": "https://avatars.githubusercontent.com/u/10770362?s=40&v=4",
          "name": "CarGuo",
          "url": "https://github.com/CarGuo"
        },
        {
          "avatar": "https://avatars.githubusercontent.com/u/34023532?s=40&v=4",
          "name": "CarGuoSmall",
          "url": "https://github.com/CarGuoSmall"
        },
        {
          "avatar": "https://avatars.githubusercontent.com/u/10363352?s=40&v=4",
          "name": "Goooler",
          "url": "https://github.com/Goooler"
        },
        {
          "avatar": "https://avatars.githubusercontent.com/u/6941555?s=40&v=4",
          "name": "fenghebaiyang",
          "url": "https://github.com/fenghebaiyang"
        },
        {
          "avatar": "https://avatars.githubusercontent.com/u/10829860?s=40&v=4",
          "name": "wangrunxiang",
          "url": "https://github.com/wangrunxiang"
        }
      ]
    },
    {
      "title": "freeok/so-novel",
      "url": "https://github.com/freeok/so-novel",
      "description": "小说下载器 | 小说下载工具 | 小说下载神器 | 免费小说 | 网络小说 | 免费下载 | 网文下载",
      "language": "Java",
      "languageColor": "#b07219",
      "stars": "2,950",
      "forks": "247",
      "addStars": "516",
      "contributors": [
        {
          "avatar": "https://avatars.githubusercontent.com/u/51998152?s=40&v=4",
          "name": "freeok",
          "url": "https://github.com/freeok"
        },
        {
          "avatar": "https://avatars.githubusercontent.com/u/16909431?s=40&v=4",
          "name": "ownia",
          "url": "https://github.com/ownia"
        },
        {
          "avatar": "https://avatars.githubusercontent.com/u/15345355?s=40&v=4",
          "name": "JaneWardSandy",
          "url": "https://github.com/JaneWardSandy"
        }
      ]
    }
  ]
}